custom_horizontal_plot/__init__.py
custom_horizontal_plot/example.py
custom_horizontal_plot/frontend/build/asset-manifest.json
custom_horizontal_plot/frontend/build/bootstrap.min.css
custom_horizontal_plot/frontend/build/bootstrap.min.css.map
custom_horizontal_plot/frontend/build/index.html
custom_horizontal_plot/frontend/build/static/css/main.982dfc3b.css
custom_horizontal_plot/frontend/build/static/css/main.982dfc3b.css.map
custom_horizontal_plot/frontend/build/static/js/main.5bec0b69.js
custom_horizontal_plot/frontend/build/static/js/main.5bec0b69.js.LICENSE.txt
custom_horizontal_plot/frontend/build/static/js/main.5bec0b69.js.map
custom_horizontal_plot-0.0.7.dist-info/LICENSE
custom_horizontal_plot-0.0.7.dist-info/METADATA
custom_horizontal_plot-0.0.7.dist-info/WHEEL
custom_horizontal_plot-0.0.7.dist-info/top_level.txt
custom_horizontal_plot-0.0.7.dist-info/RECORD
